flut/__init__.py
flut/_flut.py
flut/_flut_linux.py
flut/_flut_macos.py
flut/_flut_native.py
flut/_flut_runtime.py
flut/_flut_windows.py
flut/.flutter/build/windows/x64/runner/Release/flut.exe
flut/.flutter/build/windows/x64/runner/Release/flutter_windows.dll
flut/.flutter/build/windows/x64/runner/Release/data/app.so
flut/.flutter/build/windows/x64/runner/Release/data/icudtl.dat
flut/.flutter/build/windows/x64/runner/Release/data/flutter_assets/AssetManifest.bin
flut/.flutter/build/windows/x64/runner/Release/data/flutter_assets/FontManifest.json
flut/.flutter/build/windows/x64/runner/Release/data/flutter_assets/NOTICES.Z
flut/.flutter/build/windows/x64/runner/Release/data/flutter_assets/NativeAssetsManifest.json
flut/.flutter/build/windows/x64/runner/Release/data/flutter_assets/fonts/MaterialIcons-Regular.otf
flut/.flutter/build/windows/x64/runner/Release/data/flutter_assets/shaders/ink_sparkle.frag
flut/.flutter/build/windows/x64/runner/Release/data/flutter_assets/shaders/stretch_effect.frag
flut/flutter/material.py
flut/flutter/widgets/__init__.py
flut/flutter/widgets/basic.py
flut/flutter/widgets/framework.py
flut/flutter/widgets/implicit_animations.py
flut/flutter/widgets/painting.py
flut-0.0.0a4.dist-info/licenses/LICENSE
flut-0.0.0a4.dist-info/METADATA
flut-0.0.0a4.dist-info/WHEEL
flut-0.0.0a4.dist-info/top_level.txt
flut-0.0.0a4.dist-info/RECORD
