Metadata-Version: 2.4
Name: flut
Version: 0.0.0a4
Summary: Flutter but Python
Requires-Python: >=3.8
License-File: LICENSE
Provides-Extra: test
Requires-Dist: pytest; extra == "test"
Requires-Dist: pytest-asyncio; extra == "test"
Dynamic: license-file
